openjd/cli/__init__.py
openjd/cli/_create_argparser.py
openjd/cli/_version.py
openjd/cli/py.typed
openjd/cli/_check/__init__.py
openjd/cli/_check/_check_command.py
openjd/cli/_common/__init__.py
openjd/cli/_common/_extensions.py
openjd/cli/_common/_job_from_template.py
openjd/cli/_common/_validation_utils.py
openjd/cli/_run/__init__.py
openjd/cli/_run/_help_formatter.py
openjd/cli/_run/_run_command.py
openjd/cli/_run/_local_session/__init__.py
openjd/cli/_run/_local_session/_actions.py
openjd/cli/_run/_local_session/_logs.py
openjd/cli/_run/_local_session/_session_manager.py
openjd/cli/_schema/__init__.py
openjd/cli/_schema/_schema_command.py
openjd/cli/_summary/__init__.py
openjd/cli/_summary/_summary_command.py
openjd/cli/_summary/_summary_output.py
openjd/__main__.py
openjd_cli-0.7.4.dist-info/METADATA
openjd_cli-0.7.4.dist-info/WHEEL
openjd_cli-0.7.4.dist-info/entry_points.txt
openjd_cli-0.7.4.dist-info/licenses/LICENSE
openjd_cli-0.7.4.dist-info/licenses/NOTICE
openjd_cli-0.7.4.dist-info/RECORD
