Metadata-Version: 2.4
Name: openjd-cli
Version: 0.7.4
Summary: Provides a command-line interface for working with Open Job Description templates.
Project-URL: Homepage, https://github.com/OpenJobDescription/openjd-cli
Project-URL: Source, https://github.com/OpenJobDescription/openjd-cli
Author: Amazon Web Services
License-Expression: Apache-2.0
License-File: LICENSE
License-File: NOTICE
Classifier: Development Status :: 5 - Production/Stable
Classifier: Intended Audience :: Developers
Classifier: Intended Audience :: End Users/Desktop
Classifier: License :: OSI Approved :: Apache Software License
Classifier: Operating System :: MacOS
Classifier: Operating System :: Microsoft :: Windows
Classifier: Operating System :: POSIX :: Linux
Classifier: Programming Language :: Python
Classifier: Programming Language :: Python :: 3 :: Only
Classifier: Programming Language :: Python :: 3.9
Classifier: Programming Language :: Python :: 3.10
Classifier: Programming Language :: Python :: 3.11
Classifier: Programming Language :: Python :: 3.12
Requires-Python: >=3.9
Requires-Dist: openjd-model<0.9,>=0.8
Requires-Dist: openjd-sessions<0.11,>=0.10.3
